spi_slave.sv
module spi_slave (
    input  logic       clk,
    input  logic       rst,
    input  logic       cs_n,
    input  logic       sclk,
    input  logic       mosi,
    input  logic [7:0] tx_data,

    output logic       miso,
    output logic [7:0] rx_data,
    output logic       done
);

    logic [7:0] tx_shift;
    logic [7:0] rx_shift;
    logic [2:0] bit_count;
    logic       cs_n_d;
    logic       sclk_d;

    wire cs_active = ~cs_n;
    wire cs_start  = cs_n_d & ~cs_n;
    wire sclk_rise = sclk & ~sclk_d;
    wire sclk_fall = ~sclk & sclk_d;

    always_ff @(posedge clk) begin
        if (rst) begin
            tx_shift <= 8'b0;
            rx_shift <= 8'b0;
            rx_data <= 8'b0;
            bit_count <= 3'b0;
            miso <= 1'b0;
            done <= 1'b0;
            cs_n_d <= 1'b1;
            sclk_d <= 1'b0;
        end
        else begin
            cs_n_d <= cs_n;
            sclk_d <= sclk;
            done <= 1'b0;

            if (cs_start) begin
                tx_shift <= tx_data;
                rx_shift <= 8'b0;
                bit_count <= 3'b0;
                miso <= tx_data[7];
            end
            else if (!cs_active) begin
                miso <= 1'b0;
                bit_count <= 3'b0;
            end
            else begin
                if (sclk_rise) begin
                    rx_shift <= {rx_shift[6:0], mosi};

                    if (bit_count == 3'd7) begin
                        rx_data <= {rx_shift[6:0], mosi};
                        done <= 1'b1;
                    end
                end

                if (sclk_fall) begin
                    if (bit_count != 3'd7) begin
                        bit_count <= bit_count + 1'b1;
                        tx_shift <= {tx_shift[6:0], 1'b0};
                        miso <= tx_shift[6];
                    end
                end
            end
        end
    end

endmodule

spi_master.sv
module spi_master #(
    parameter CLK_DIV = 4
)(
    input  logic       clk,
    input  logic       rst,
    input  logic       start,
    input  logic [7:0] tx_data,
    input  logic       miso,

    output logic [7:0] rx_data,
    output logic       busy,
    output logic       done,
    output logic       sclk,
    output logic       mosi,
    output logic       cs_n
);

    logic [7:0] tx_shift;
    logic [7:0] rx_shift;
    logic [2:0] bit_count;
    logic [15:0] clk_count;

    always_ff @(posedge clk) begin
        if (rst) begin
            tx_shift  <= 8'b0;
            rx_shift  <= 8'b0;
            rx_data   <= 8'b0;
            bit_count <= 3'b0;
            clk_count <= 16'b0;
            busy      <= 1'b0;
            done      <= 1'b0;
            sclk      <= 1'b0;
            mosi      <= 1'b0;
            cs_n      <= 1'b1;
        end
        else begin
            done <= 1'b0;

            if (!busy) begin
                if (start) begin
                    tx_shift  <= tx_data;
                    rx_shift  <= 8'b0;
                    bit_count <= 3'b0;
                    clk_count <= 16'b0;
                    busy      <= 1'b1;
                    cs_n      <= 1'b0;
                    sclk      <= 1'b0;
                    mosi      <= tx_data[7];
                end
            end
            else begin
                if (clk_count == CLK_DIV - 1) begin
                    clk_count <= 16'b0;

                    if (sclk == 1'b0) begin
                        sclk <= 1'b1;
                        rx_shift <= {rx_shift[6:0], miso};

                        if (bit_count == 3'd7)
                            rx_data <= {rx_shift[6:0], miso};
                    end
                    else begin
                        sclk <= 1'b0;

                        if (bit_count == 3'd7) begin
                            busy <= 1'b0;
                            done <= 1'b1;
                            cs_n <= 1'b1;
                            mosi <= 1'b0;
                        end
                        else begin
                            bit_count <= bit_count + 1'b1;
                            tx_shift <= {tx_shift[6:0], 1'b0};
                            mosi <= tx_shift[6];
                        end
                    end
                end
                else begin
                    clk_count <= clk_count + 1'b1;
                end
            end
        end
    end

endmodule

spi_master_slave_top.sv
module spi_master_slave_top #(
    parameter CLK_DIV = 4
)(
    input  logic       clk,
    input  logic       rst,
    input  logic       start,
    input  logic [7:0] master_tx_data,
    input  logic [7:0] slave_tx_data,

    output logic [7:0] master_rx_data,
    output logic [7:0] slave_rx_data,
    output logic       busy,
    output logic       done,
    output logic       spi_sclk,
    output logic       spi_mosi,
    output logic       spi_miso,
    output logic       spi_cs_n
);

    logic [7:0] master_rx;
    logic [7:0] slave_rx;
    logic       master_busy;
    logic       master_done;
    logic       master_sclk;
    logic       master_mosi;
    logic       master_cs_n;
    logic       slave_miso;
    logic       slave_done;

    spi_master #(
        .CLK_DIV(CLK_DIV)
    ) master_inst (
        .clk(clk),
        .rst(rst),
        .start(start),
        .tx_data(master_tx_data),
        .miso(slave_miso),
        .rx_data(master_rx),
        .busy(master_busy),
        .done(master_done),
        .sclk(master_sclk),
        .mosi(master_mosi),
        .cs_n(master_cs_n)
    );

    spi_slave slave_inst (
        .clk(clk),
        .rst(rst),
        .cs_n(master_cs_n),
        .sclk(master_sclk),
        .mosi(master_mosi),
        .tx_data(slave_tx_data),
        .miso(slave_miso),
        .rx_data(slave_rx),
        .done(slave_done)
    );

    assign master_rx_data = master_rx;
    assign slave_rx_data  = slave_rx;
    assign busy           = master_busy;
    assign done           = master_done;
    assign spi_sclk       = master_sclk;
    assign spi_mosi       = master_mosi;
    assign spi_miso       = slave_miso;
    assign spi_cs_n       = master_cs_n;

endmodule

tb_spi_master_slave.sv
`timescale 1ns/1ps

module tb_spi_master_slave;

    logic       clk;
    logic       rst;
    logic       start;
    logic [7:0] master_tx_data;
    logic [7:0] slave_tx_data;

    logic [7:0] master_rx_data;
    logic [7:0] slave_rx_data;
    logic       busy;
    logic       done;
    logic       spi_sclk;
    logic       spi_mosi;
    logic       spi_miso;
    logic       spi_cs_n;

    spi_master_slave_top #(
        .CLK_DIV(4)
    ) dut (
        .clk(clk),
        .rst(rst),
        .start(start),
        .master_tx_data(master_tx_data),
        .slave_tx_data(slave_tx_data),
        .master_rx_data(master_rx_data),
        .slave_rx_data(slave_rx_data),
        .busy(busy),
        .done(done),
        .spi_sclk(spi_sclk),
        .spi_mosi(spi_mosi),
        .spi_miso(spi_miso),
        .spi_cs_n(spi_cs_n)
    );

    initial begin
        clk = 1'b0;
        forever #5 clk = ~clk;
    end

    initial begin
        $dumpfile("spi.vcd");
        $dumpvars(0, tb_spi_master_slave);

        rst = 1'b1;
        start = 1'b0;
        master_tx_data = 8'hA5;
        slave_tx_data = 8'h3C;

        #30;
        rst = 1'b0;

        #20;
        start = 1'b1;

        #10;
        start = 1'b0;

        wait(done);

        #20;

        $display("Master TX Data = %h", master_tx_data);
        $display("Slave TX Data  = %h", slave_tx_data);
        $display("Master RX Data = %h", master_rx_data);
        $display("Slave RX Data  = %h", slave_rx_data);

        if (master_rx_data == slave_tx_data)
            $display("MASTER RX TEST: PASS");
        else
            $display("MASTER RX TEST: FAIL");

        if (slave_rx_data == master_tx_data)
            $display("SLAVE RX TEST: PASS");
        else
            $display("SLAVE RX TEST: FAIL");

        #20;
        $finish;
    end

endmodule

spi.vcd
$date
	Mon Sep 14 20:09:08 2026
$end
$version
	Icarus Verilog
$end
$timescale
	1ps
$end
$scope module tb_spi_master_slave $end
$var wire 1 ! spi_sclk $end
$var wire 1 " spi_mosi $end
$var wire 1 # spi_miso $end
$var wire 1 $ spi_cs_n $end
$var wire 8 % slave_rx_data [7:0] $end
$var wire 8 & master_rx_data [7:0] $end
$var wire 1 ' done $end
$var wire 1 ( busy $end
$var reg 1 ) clk $end
$var reg 8 * master_tx_data [7:0] $end
$var reg 1 + rst $end
$var reg 8 , slave_tx_data [7:0] $end
$var reg 1 - start $end
$scope module dut $end
$var wire 1 ( busy $end
$var wire 1 ) clk $end
$var wire 1 ' done $end
$var wire 8 . master_rx_data [7:0] $end
$var wire 8 / master_tx_data [7:0] $end
$var wire 1 + rst $end
$var wire 8 0 slave_rx_data [7:0] $end
$var wire 8 1 slave_tx_data [7:0] $end
$var wire 1 $ spi_cs_n $end
$var wire 1 # spi_miso $end
$var wire 1 " spi_mosi $end
$var wire 1 ! spi_sclk $end
$var wire 1 - start $end
$var wire 8 2 slave_rx [7:0] $end
$var wire 1 3 slave_miso $end
$var wire 1 4 slave_done $end
$var wire 1 5 master_sclk $end
$var wire 8 6 master_rx [7:0] $end
$var wire 1 7 master_mosi $end
$var wire 1 8 master_done $end
$var wire 1 9 master_cs_n $end
$var wire 1 : master_busy $end
$var parameter 32 ; CLK_DIV $end
$scope module master_inst $end
$var wire 1 ) clk $end
$var wire 1 + rst $end
$var wire 1 - start $end
$var wire 8 < tx_data [7:0] $end
$var wire 1 3 miso $end
$var parameter 32 = CLK_DIV $end
$var reg 3 > bit_count [2:0] $end
$var reg 1 : busy $end
$var reg 16 ? clk_count [15:0] $end
$var reg 1 9 cs_n $end
$var reg 1 8 done $end
$var reg 1 7 mosi $end
$var reg 8 @ rx_data [7:0] $end
$var reg 8 A rx_shift [7:0] $end
$var reg 1 5 sclk $end
$var reg 8 B tx_shift [7:0] $end
$upscope $end
$scope module slave_inst $end
$var wire 1 ) clk $end
$var wire 1 C cs_active $end
$var wire 1 9 cs_n $end
$var wire 1 D cs_start $end
$var wire 1 7 mosi $end
$var wire 1 + rst $end
$var wire 1 5 sclk $end
$var wire 1 E sclk_fall $end
$var wire 1 F sclk_rise $end
$var wire 8 G tx_data [7:0] $end
$var reg 3 H bit_count [2:0] $end
$var reg 1 I cs_n_d $end
$var reg 1 4 done $end
$var reg 1 3 miso $end
$var reg 8 J rx_data [7:0] $end
$var reg 8 K rx_shift [7:0] $end
$var reg 1 L sclk_d $end
$var reg 8 M tx_shift [7:0] $end
$upscope $end
$upscope $end
$upscope $end
$enddefinitions $end
$comment Show the parameter values. $end
$dumpall
b100 =
b100 ;
$end
#0
$dumpvars
bx M
xL
bx K
bx J
xI
bx H
b111100 G
xF
xE
xD
xC
bx B
bx A
bx @
bx ?
bx >
b10100101 <
x:
x9
x8
x7
bx 6
x5
x4
x3
bx 2
b111100 1
bx 0
b10100101 /
bx .
0-
b111100 ,
1+
b10100101 *
0)
x(
x'
bx &
bx %
x$
x#
x"
x!
$end
#5000
0D
0C
0F
0E
1$
19
0"
07
0!
05
0'
08
0(
0:
b0 ?
b0 >
b0 &
b0 .
b0 6
b0 @
b0 A
b0 B
0L
1I
04
0#
03
b0 H
b0 %
b0 0
b0 2
b0 J
b0 K
b0 M
1)
#10000
0)
#15000
1)
#20000
0)
#25000
1)
#30000
0)
0+
#35000
1)
#40000
0)
#45000
1)
#50000
0)
1-
#55000
1D
1C
1"
17
0$
09
1(
1:
b10100101 B
1)
#60000
0)
0-
#65000
0D
b1 ?
b111100 M
0I
1)
#70000
0)
#75000
b10 ?
1)
#80000
0)
#85000
b11 ?
1)
#90000
0)
#95000
1F
1!
15
b0 ?
1)
#100000
0)
#105000
0F
b1 ?
b1 K
1L
1)
#110000
0)
#115000
b10 ?
1)
#120000
0)
#125000
b11 ?
1)
#130000
0)
#135000
1E
0"
07
b1001010 B
b1 >
0!
05
b0 ?
1)
#140000
0)
#145000
0E
b1 ?
b1111000 M
b1 H
0L
1)
#150000
0)
#155000
b10 ?
1)
#160000
0)
#165000
b11 ?
1)
#170000
0)
#175000
1F
1!
15
b0 ?
1)
#180000
0)
#185000
0F
b1 ?
b10 K
1L
1)
#190000
0)
#195000
b10 ?
1)
#200000
0)
#205000
b11 ?
1)
#210000
0)
#215000
1E
1"
17
b10010100 B
b10 >
0!
05
b0 ?
1)
#220000
0)
#225000
0E
b1 ?
1#
13
b11110000 M
b10 H
0L
1)
#230000
0)
#235000
b10 ?
1)
#240000
0)
#245000
b11 ?
1)
#250000
0)
#255000
1F
b1 A
1!
15
b0 ?
1)
#260000
0)
#265000
0F
b1 ?
b101 K
1L
1)
#270000
0)
#275000
b10 ?
1)
#280000
0)
#285000
b11 ?
1)
#290000
0)
#295000
1E
0"
07
b101000 B
b11 >
0!
05
b0 ?
1)
#300000
0)
#305000
0E
b1 ?
b11100000 M
b11 H
0L
1)
#310000
0)
#315000
b10 ?
1)
#320000
0)
#325000
b11 ?
1)
#330000
0)
#335000
1F
b11 A
1!
15
b0 ?
1)
#340000
0)
#345000
0F
b1 ?
b1010 K
1L
1)
#350000
0)
#355000
b10 ?
1)
#360000
0)
#365000
b11 ?
1)
#370000
0)
#375000
1E
b1010000 B
b100 >
0!
05
b0 ?
1)
#380000
0)
#385000
0E
b1 ?
b11000000 M
b100 H
0L
1)
#390000
0)
#395000
b10 ?
1)
#400000
0)
#405000
b11 ?
1)
#410000
0)
#415000
1F
b111 A
1!
15
b0 ?
1)
#420000
0)
#425000
0F
b1 ?
b10100 K
1L
1)
#430000
0)
#435000
b10 ?
1)
#440000
0)
#445000
b11 ?
1)
#450000
0)
#455000
1E
1"
17
b10100000 B
b101 >
0!
05
b0 ?
1)
#460000
0)
#465000
0E
b1 ?
b10000000 M
b101 H
0L
1)
#470000
0)
#475000
b10 ?
1)
#480000
0)
#485000
b11 ?
1)
#490000
0)
#495000
1F
b1111 A
1!
15
b0 ?
1)
#500000
0)
#505000
0F
b1 ?
b101001 K
1L
1)
#510000
0)
#515000
b10 ?
1)
#520000
0)
#525000
b11 ?
1)
#530000
0)
#535000
1E
0"
07
b1000000 B
b110 >
0!
05
b0 ?
1)
#540000
0)
#545000
0E
b1 ?
0#
03
b0 M
b110 H
0L
1)
#550000
0)
#555000
b10 ?
1)
#560000
0)
#565000
b11 ?
1)
#570000
0)
#575000
1F
b11110 A
1!
15
b0 ?
1)
#580000
0)
#585000
0F
b1 ?
b1010010 K
1L
1)
#590000
0)
#595000
b10 ?
1)
#600000
0)
#605000
b11 ?
1)
#610000
0)
#615000
1E
1"
17
b10000000 B
b111 >
0!
05
b0 ?
1)
#620000
0)
#625000
0E
b1 ?
b111 H
0L
1)
#630000
0)
#635000
b10 ?
1)
#640000
0)
#645000
b11 ?
1)
#650000
0)
#655000
1F
b111100 &
b111100 .
b111100 6
b111100 @
b111100 A
1!
15
b0 ?
1)
#660000
0)
#665000
0F
b1 ?
14
b10100101 %
b10100101 0
b10100101 2
b10100101 J
b10100101 K
1L
1)
#670000
0)
#675000
04
b10 ?
1)
#680000
0)
#685000
b11 ?
1)
#690000
0)
#695000
1E
0C
0"
07
1$
19
1'
18
0(
0:
0!
05
b0 ?
1)
#700000
0)
#705000
0E
0'
08
b0 H
0L
1I
1)
